README.rst
setup.py
pyramid_saaudittrail/__init__.py
pyramid_saaudittrail/ajson.py
pyramid_saaudittrail/models.py
pyramid_saaudittrail.egg-info/PKG-INFO
pyramid_saaudittrail.egg-info/SOURCES.txt
pyramid_saaudittrail.egg-info/dependency_links.txt
pyramid_saaudittrail.egg-info/entry_points.txt
pyramid_saaudittrail.egg-info/not-zip-safe
pyramid_saaudittrail.egg-info/requires.txt
pyramid_saaudittrail.egg-info/top_level.txt