Metadata-Version: 1.0
Name: pyramid-saaudittrail
Version: 0.1
Summary: Automatically audit db changes for pyramid and sqlalchemy
Home-page: UNKNOWN
Author: Nathan Van Gheem
Author-email: vangheem@gmail.com
License: UNKNOWN
Platform: UNKNOWN
Classifier: Framework :: Pyramid
